setup.py
ahg48/__init__.py
ahg48.egg-info/PKG-INFO
ahg48.egg-info/SOURCES.txt
ahg48.egg-info/dependency_links.txt
ahg48.egg-info/entry_points.txt
ahg48.egg-info/top_level.txt