Metadata-Version: 1.0
Name: ahg48
Version: 0.1.3
Summary: AHG 48
Home-page: https://github.com/rch850/ahg48
Author: rch850
Author-email: rich850@gmail.com
License: Apache2
Platform: UNKNOWN
